kommando/__init__.py
kommando/base.py
kommando/loader.py
kommando/defaults/errors.py
kommando/defaults/extensions.py
kommando/defaults/modifiers.py
kommando/defaults/summons.py
kommando/defaults/templates.py
kommando/defaults/types.py
kommando-1.3.2.dist-info/METADATA
kommando-1.3.2.dist-info/RECORD
kommando-1.3.2.dist-info/WHEEL
kommando-1.3.2.dist-info/top_level.txt
