Metadata-Version: 2.1
Name: kommando
Version: 1.3.2
Summary: A very extensible command parser for discord.py [rewrite]
Home-page: https://github.com/Naranbataar/Kommando.py
Author: Andre Augusto
Author-email: UNKNOWN
License: UNKNOWN
Platform: UNKNOWN
Classifier: Framework :: AsyncIO
Classifier: Development Status :: 5 - Production/Stable
Classifier: Programming Language :: Python :: 3 :: Only
Classifier: Programming Language :: Python :: 3.6
Classifier: Programming Language :: Python :: 3.7
Classifier: Programming Language :: Python :: 3.8
Classifier: License :: OSI Approved :: MIT License
Classifier: Operating System :: OS Independent
Classifier: Intended Audience :: Developers
Requires-Python: >=3.6.0
